git_smart_clone/__init__.py
git_smart_clone/smart_clone.py
git_smart_clone-1.0.0.dist-info/METADATA
git_smart_clone-1.0.0.dist-info/WHEEL
git_smart_clone-1.0.0.dist-info/entry_points.txt
git_smart_clone-1.0.0.dist-info/licenses/LICENSE
git_smart_clone-1.0.0.dist-info/RECORD
