Metadata-Version: 2.4
Name: git-smart-clone
Version: 1.0.0
Summary: A simple git extension that clones a git directory to subfolder based on the git url
Author-email: Sam Phinizy <sam@phin.tech>
License: MIT
License-File: LICENSE
Requires-Python: >=3.10
Requires-Dist: click>=8.1.3
